lamo/__init__.py
lamo/llms.py
lamo-0.0.1.dist-info/METADATA
lamo-0.0.1.dist-info/WHEEL
lamo-0.0.1.dist-info/top_level.txt
lamo-0.0.1.dist-info/RECORD
