Metadata-Version: 2.1
Name: lamo
Version: 0.0.1
Summary: Unix language driver for software 2.0
Author-email: Jason Wilkes <notarealdeveloper@gmail.com>
Project-URL: source, https://github.com/notarealdeveloper/llms
Project-URL: download, https://pypi.org/project/llms/#files
Provides-Extra: develop
Requires-Dist: build ; extra == 'develop'
Requires-Dist: pytest ; extra == 'develop'
